Metadata-Version: 2.1
Name: conorm
Version: 1.1.1
Summary: Normalization methods for RNA-seq count data.
Home-page: https://gitlab.com/georgy.m/conorm
Author: Georgy Meshcheryakov
Author-email: i@georgy.top
License: UNKNOWN
Platform: UNKNOWN
Classifier: Programming Language :: Python :: 3.7
Classifier: Programming Language :: Python :: 3.8
Classifier: Programming Language :: Python :: 3.9
Classifier: Programming Language :: Python :: 3.10
Classifier: Development Status :: 5 - Production/Stable
Classifier: Topic :: Scientific/Engineering
Classifier: Operating System :: OS Independent
Requires-Python: >=3.7
